{
  "email": {
    "limit": 5,
    "serial": "321744"
  },
  "posts": [
    {
      "id": 1,
      "title": "json-server"
    }
  ],
  "user": [
    {
      "id": "1",
      "mail": "superadmin@example.com",
      "level": "super",
      "name": "슈퍼관리자",
      "division": "경영지원",
      "pw": "qwer1234"
    },
    {
      "id": "2",
      "mail": "admin1@example.com",
      "level": "admin",
      "name": "관리자",
      "division": "경영지원",
      "pw": "qwer1234"
    },
    {
      "id": "3",
      "mail": "admin2@example.com",
      "level": "admin",
      "name": "관리자",
      "division": "경영지원",
      "pw": "qwer1234"
    },
    {
      "id": "4",
      "mail": "admin3@example.com",
      "level": "admin",
      "name": "관리자",
      "division": "경영지원",
      "pw": "qwer1234"
    },
    {
      "id": "5",
      "mail": "sub1@example.com",
      "level": "sub",
      "name": "서브관리자",
      "division": "경영지원",
      "pw": "qwer1234"
    },
    {
      "id": "6",
      "mail": "sub2@example.com",
      "level": "sub",
      "name": "서브관리자",
      "division": "경영지원",
      "pw": "qwer1234"
    },
    {
      "id": "7",
      "mail": "temp1@example.com",
      "level": "temp",
      "name": "준회원",
      "division": "경영지원",
      "pw": "qwer1234"
    },
    {
      "id": "8",
      "mail": "temp2@example.com",
      "level": "temp",
      "name": "준회원",
      "division": "경영지원"
    },
    {
      "id": "9",
      "mail": "asdf@asdf.com",
      "level": "temp",
      "name": "asdf",
      "pw": "qwer1234"
    }
  ],
  "log": [
    {
      "id": "home",
      "logs": [
        {
          "title": "aaa@admin.com",
          "content": "배너1234.jpg 등록",
          "date": "2021-05-27T21:13:40Z"
        },
        {
          "title": "aaa@admin.com",
          "content": "배너123asdf4.jpg 삭제",
          "date": "2021-05-26T01:13:40Z"
        },
        {
          "title": "aaa@admin.com",
          "content": "sns youtube link 변경",
          "date": "2021-05-26T10:13:40Z"
        },
        {
          "title": "aaa@admin.com",
          "content": "메인 영상 링크 변경",
          "date": "2021-05-25T12:13:40Z"
        },
        {
          "title": "작업자",
          "content": "작업내용",
          "date": "2021-05-27T17:13:40Z"
        },
        {
          "title": "작업자",
          "content": "작업내용",
          "date": "2021-05-27T17:13:40Z"
        },
        {
          "title": "작업자의 긴 아이디가 여기에 위치합니다.",
          "content": "작업내용이 길면 이렇게 보입니다.",
          "date": "2021-05-27T17:13:40Z"
        },
        {
          "title": "작업자",
          "content": "작업내용",
          "date": "2021-05-27T17:13:40Z"
        },
        {
          "title": "aaa@admin.com",
          "content": "배너1234.jpg 등록",
          "date": "2021-05-27T17:13:40Z"
        },
        {
          "title": "aaa@admin.com",
          "content": "배너123asdf4.jpg 삭제",
          "date": "2021-05-27T17:13:40Z"
        },
        {
          "title": "aaa@admin.com",
          "content": "sns youtube link 변경",
          "date": "2021-05-27T17:13:40Z"
        },
        {
          "title": "aaa@admin.com",
          "content": "메인 영상 링크 변경",
          "date": "2021-05-27T17:13:40Z"
        },
        {
          "title": "작업자",
          "content": "작업내용",
          "date": "2021-05-27T17:13:40Z"
        },
        {
          "title": "작업자",
          "content": "작업내용",
          "date": "2021-05-27T17:13:40Z"
        },
        {
          "title": "작업자의 긴 아이디가 여기에 위치합니다.",
          "content": "작업내용이 길면 이렇게 보입니다.",
          "date": "2021-05-27T17:13:40Z"
        },
        {
          "title": "작업자",
          "content": "작업내용",
          "date": "2021-05-27T17:13:40Z"
        },
        {
          "title": "작업자",
          "content": "작업내용",
          "date": "2021-05-27T17:13:40Z"
        },
        {
          "title": "작업자",
          "content": "작업내용",
          "date": "2021-05-27T17:13:40Z"
        },
        {
          "title": "작업자",
          "content": "작업내용",
          "date": "2021-05-27T17:13:40Z"
        },
        {
          "title": "작업자",
          "content": "작업내용",
          "date": "2021-05-27T17:13:40Z"
        },
        {
          "title": "작업자",
          "content": "작업내용",
          "date": "2021-05-27T17:13:40Z"
        },
        {
          "title": "작업자",
          "content": "작업내용",
          "date": "2021-05-27T17:13:40Z"
        },
        {
          "title": "작업자",
          "content": "작업내용",
          "date": "2021-05-27T17:13:40Z"
        },
        {
          "title": "작업자",
          "content": "작업내용",
          "date": "2021-05-27T17:13:40Z"
        },
        {
          "title": "작업자",
          "content": "작업내용",
          "date": "2021-05-27T17:13:40Z"
        },
        {
          "title": "작업자",
          "content": "작업내용",
          "date": "2021-05-27T17:13:40Z"
        },
        {
          "title": "작업자",
          "content": "작업내용",
          "date": "2021-05-27T17:13:40Z"
        },
        {
          "title": "작업자",
          "content": "작업내용",
          "date": "2021-05-27T17:13:40Z"
        },
        {
          "title": "작업자",
          "content": "작업내용",
          "date": "2021-05-27T17:13:40Z"
        },
        {
          "title": "작업자",
          "content": "작업내용",
          "date": "2021-05-27T17:13:40Z"
        },
        {
          "title": "작업자",
          "content": "작업내용",
          "date": "2021-05-27T17:13:40Z"
        },
        {
          "title": "작업자",
          "content": "작업내용",
          "date": "2021-05-27T17:13:40Z"
        },
        {
          "title": "작업자",
          "content": "작업내용",
          "date": "2021-05-27T17:13:40Z"
        },
        {
          "title": "작업자",
          "content": "작업내용",
          "date": "2021-05-27T17:13:40Z"
        },
        {
          "title": "작업자",
          "content": "작업내용",
          "date": "2021-05-27T17:13:40Z"
        },
        {
          "title": "작업자",
          "content": "작업내용",
          "date": "2021-05-27T17:13:40Z"
        },
        {
          "title": "작업자",
          "content": "작업내용",
          "date": "2021-05-27T17:13:40Z"
        },
        {
          "title": "작업자",
          "content": "작업내용",
          "date": "2021-05-27T17:13:40Z"
        },
        {
          "title": "작업자",
          "content": "작업내용",
          "date": "2021-05-27T17:13:40Z"
        },
        {
          "title": "작업자",
          "content": "작업내용",
          "date": "2021-05-27T17:13:40Z"
        },
        {
          "title": "작업자",
          "content": "작업내용",
          "date": "2021-05-27T17:13:40Z"
        },
        {
          "title": "작업자",
          "content": "작업내용",
          "date": "2021-05-27T17:13:40Z"
        },
        {
          "title": "작업자",
          "content": "작업내용",
          "date": "2021-05-27T17:13:40Z"
        },
        {
          "title": "작업자",
          "content": "작업내용",
          "date": "2021-05-27T17:13:40Z"
        },
        {
          "title": "작업자",
          "content": "작업내용",
          "date": "2021-05-27T17:13:40Z"
        },
        {
          "title": "작업자",
          "content": "작업내용",
          "date": "2021-05-27T17:13:40Z"
        },
        {
          "title": "작업자",
          "content": "작업내용",
          "date": "2021-05-27T17:13:40Z"
        },
        {
          "title": "작업자",
          "content": "작업내용",
          "date": "2021-05-27T17:13:40Z"
        },
        {
          "title": "작업자",
          "content": "작업내용",
          "date": "2021-05-27T17:13:40Z"
        },
        {
          "title": "작업자",
          "content": "작업내용",
          "date": "2021-05-27T17:13:40Z"
        },
        {
          "title": "작업자",
          "content": "작업내용",
          "date": "2021-05-27T17:13:40Z"
        },
        {
          "title": "작업자",
          "content": "작업내용",
          "date": "2021-05-27T17:13:40Z"
        },
        {
          "title": "작업자",
          "content": "작업내용",
          "date": "2021-05-27T17:13:40Z"
        },
        {
          "title": "작업자",
          "content": "작업내용",
          "date": "2021-05-27T17:13:40Z"
        },
        {
          "title": "작업자",
          "content": "작업내용",
          "date": "2021-05-27T17:13:40Z"
        },
        {
          "title": "작업자",
          "content": "작업내용",
          "date": "2021-05-27T17:13:40Z"
        },
        {
          "title": "작업자",
          "content": "작업내용",
          "date": "2021-05-27T17:13:40Z"
        },
        {
          "title": "작업자",
          "content": "작업내용",
          "date": "2021-05-27T17:13:40Z"
        },
        {
          "title": "작업자",
          "content": "작업내용",
          "date": "2021-05-27T17:13:40Z"
        },
        {
          "title": "작업자",
          "content": "작업내용",
          "date": "2021-05-27T17:13:40Z"
        },
        {
          "title": "작업자",
          "content": "작업내용",
          "date": "2021-05-27T17:13:40Z"
        },
        {
          "title": "작업자",
          "content": "작업내용",
          "date": "2021-05-27T17:13:40Z"
        },
        {
          "title": "작업자",
          "content": "작업내용",
          "date": "2021-05-27T17:13:40Z"
        },
        {
          "title": "작업자",
          "content": "작업내용",
          "date": "2021-05-27T17:13:40Z"
        },
        {
          "title": "작업자",
          "content": "작업내용",
          "date": "2021-05-27T17:13:40Z"
        },
        {
          "title": "작업자",
          "content": "작업내용",
          "date": "2021-05-27T17:13:40Z"
        },
        {
          "title": "작업자",
          "content": "작업내용",
          "date": "2021-05-27T17:13:40Z"
        },
        {
          "title": "작업자",
          "content": "작업내용",
          "date": "2021-05-27T17:13:40Z"
        },
        {
          "title": "작업자",
          "content": "작업내용",
          "date": "2021-05-27T17:13:40Z"
        },
        {
          "title": "작업자",
          "content": "작업내용",
          "date": "2021-05-27T17:13:40Z"
        },
        {
          "title": "작업자",
          "content": "작업내용",
          "date": "2021-05-27T17:13:40Z"
        },
        {
          "title": "작업자",
          "content": "작업내용",
          "date": "2021-05-27T17:13:40Z"
        },
        {
          "title": "작업자",
          "content": "작업내용",
          "date": "2021-05-27T17:13:40Z"
        },
        {
          "title": "작업자",
          "content": "작업내용",
          "date": "2021-05-27T17:13:40Z"
        },
        {
          "title": "작업자",
          "content": "작업내용",
          "date": "2021-05-27T17:13:40Z"
        },
        {
          "title": "작업자",
          "content": "작업내용",
          "date": "2021-05-27T17:13:40Z"
        },
        {
          "title": "작업자",
          "content": "작업내용",
          "date": "2021-05-27T17:13:40Z"
        },
        {
          "title": "작업자",
          "content": "작업내용",
          "date": "2021-05-27T17:13:40Z"
        },
        {
          "title": "작업자",
          "content": "작업내용",
          "date": "2021-05-27T17:13:40Z"
        },
        {
          "title": "작업자",
          "content": "작업내용",
          "date": "2021-05-27T17:13:40Z"
        },
        {
          "title": "작업자",
          "content": "작업내용",
          "date": "2021-05-27T17:13:40Z"
        },
        {
          "title": "작업자",
          "content": "작업내용",
          "date": "2021-05-27T17:13:40Z"
        },
        {
          "title": "작업자",
          "content": "작업내용",
          "date": "2021-05-27T17:13:40Z"
        },
        {
          "title": "작업자",
          "content": "작업내용",
          "date": "2021-05-27T17:13:40Z"
        },
        {
          "title": "작업자",
          "content": "작업내용",
          "date": "2021-05-27T17:13:40Z"
        },
        {
          "title": "작업자",
          "content": "작업내용",
          "date": "2021-05-27T17:13:40Z"
        },
        {
          "title": "작업자",
          "content": "작업내용",
          "date": "2021-05-27T17:13:40Z"
        },
        {
          "title": "작업자",
          "content": "작업내용",
          "date": "2021-05-27T17:13:40Z"
        },
        {
          "title": "작업자",
          "content": "작업내용",
          "date": "2021-05-27T17:13:40Z"
        }
      ]
    },
    {
      "id": "notice",
      "logs": [
        {
          "title": "aaa@admin.com",
          "content": "게시글 등록",
          "date": "2021-04-14 11:00pm"
        },
        {
          "title": "aaa@admin.com",
          "content": "게시글 삭제",
          "date": "2021-04-14 11:00pm"
        },
        {
          "title": "작업자",
          "content": "작업내용",
          "date": "2021-05-27T17:13:40Z"
        }
      ]
    },
    {
      "id": "artist",
      "logs": [
        {
          "title": "aaa@admin.com",
          "content": "아티스트 등록",
          "date": "2021-04-14 11:00pm"
        },
        {
          "title": "aaa@admin.com",
          "content": "아티스트 삭제",
          "date": "2021-04-14 11:00pm"
        },
        {
          "title": "작업자",
          "content": "작업내용",
          "date": "2021-05-27T17:13:40Z"
        }
      ]
    },
    {
      "id": "admin",
      "logs": [
        {
          "title": "aaa@admin.com",
          "content": "아티스트 등록",
          "date": "2021-04-14 11:00pm"
        },
        {
          "title": "aaa@admin.com",
          "content": "아티스트 삭제",
          "date": "2021-04-14 11:00pm"
        },
        {
          "title": "작업자",
          "content": "작업내용",
          "date": "2021-05-27T17:13:40Z"
        }
      ]
    }
  ],
  "home": {
    "homeNo": "1",
    "bannerList": [
      {
        "no": "1",
        "name": "asdfasdfasd.jpg",
        "url": "https://adsfasdfasf.com"
      },
      {
        "no": "2",
        "name": "hello.jpg",
        "url": "https://camo.githubusercontent.com/100995ad676f7299b746dbe16055485aee91114e14673c7b8dde9bb0c81dc3c4/68747470733a2f2f696d616765732e73667463646e2e6e65742f696d616765732f745f6170702d636f7665722d6c2c665f6175746f2f702f63653265636536302d396233322d313165362d393561622d3030313633656438333365372f3236303636333731302f7468652d746573742d66756e2d666f722d667269656e64732d73637265656e73686f742e6a7067"
      }
    ],
    "snsList": [
      {
        "name": "Youtube",
        "url": "www.youtube.com",
        "show": true
      },
      {
        "name": "Instagram",
        "url": "",
        "show": false
      },
      {
        "name": "Facebook",
        "url": "www.facebook.com",
        "show": true
      },
      {
        "name": "Twitter",
        "url": "",
        "show": false
      },
      {
        "name": "SoundCloud",
        "url": "",
        "show": false
      }
    ],
    "videoUrl": "https://www.youtube.com/abcde"
  },
  "homeupload": {
    "homeNo": "2",
    "bannerList": [
      {
        "no": "1",
        "name": "asdfasdfasd.jpg",
        "url": "https://adsfasdfasf.com"
      },
      {
        "no": "2",
        "name": "hello.jpg",
        "url": "https://camo.githubusercontent.com/100995ad676f7299b746dbe16055485aee91114e14673c7b8dde9bb0c81dc3c4/68747470733a2f2f696d616765732e73667463646e2e6e65742f696d616765732f745f6170702d636f7665722d6c2c665f6175746f2f702f63653265636536302d396233322d313165362d393561622d3030313633656438333365372f3236303636333731302f7468652d746573742d66756e2d666f722d667269656e64732d73637265656e73686f742e6a7067"
      },
      {
        "no": "",
        "name": "",
        "url": ""
      },
      {
        "no": "",
        "name": "",
        "url": ""
      }
    ],
    "snsList": [
      {
        "name": "Youtube",
        "url": "www.youtube.com",
        "show": true
      },
      {
        "name": "Instagram",
        "url": "",
        "show": false
      },
      {
        "name": "Facebook",
        "url": "www.facebook.com",
        "show": true
      },
      {
        "name": "Twitter",
        "url": "",
        "show": false
      },
      {
        "name": "SoundCloud",
        "url": "",
        "show": false
      }
    ],
    "videoUrl": "https://www.youtube.com/abcde"
  },
  "noticelist": [
    {
      "no": 1,
      "title": "[안내]BOBBY 2nd ALBUM [LUCKY MAN]& KIT ALBUM 발매",
      "create_time": "2021-05-27T17:13:40Z",
      "update_time": "2021-05-27T17:13:40Z"
    },
    {
      "no": 2,
      "title": "[안내]B.I 구독 서비스 알림",
      "create_time": "2021-05-27T17:13:40Z",
      "update_time": "2021-05-27T17:13:40Z"
    },
    {
      "no": 3,
      "title": "[안내] BOBY....",
      "create_time": "2021-05-27T17:13:40Z",
      "update_time": "2021-05-27T17:13:40Z"
    },
    {
      "no": 4,
      "title": "[공지] 온라인 콘서트 티켓 오픈 공지",
      "create_time": "2021-05-27T17:13:40Z",
      "update_time": "2021-05-27T17:13:40Z"
    },
    {
      "no": 5,
      "title": "Lorem ipsum dolor sit amet, consectetur adipiscing elit. Aenean ac hendrerit ligula. Proin dignissim mollis odio, eu gravida metus ven",
      "create_time": "2021-05-27T17:13:40Z",
      "update_time": "2021-05-27T17:13:40Z"
    },
    {
      "no": 6,
      "title": "r lorem sodales a. Class aptent taciti sociosqu ad litora tore",
      "create_time": "2021-05-27T17:13:40Z",
      "update_time": "2021-05-27T17:13:40Z"
    },
    {
      "no": 7,
      "title": " non semper lacinia. Proin sit amet hendrerit nulla, nec sollicitudin enim.",
      "create_time": "2021-05-27T17:13:40Z",
      "update_time": "2021-05-27T17:13:40Z"
    },
    {
      "no": 8,
      "title": " Vivamus nec mauris vitae sapien cursus elementum. Sed sed suscipit justo, ut tium faucibus dolor at scelerisque",
      "create_time": "2021-05-27T17:13:40Z",
      "update_time": "2021-05-27T17:13:40Z"
    },
    {
      "no": "9",
      "title": " Vivamus nec mauris vitae sapien cursus elementum. Sed sed suscipit justo, ut tium faucibus dolor at scelerisque",
      "create_time": "2021-05-27T17:13:40Z",
      "update_time": "2021-05-27T17:13:40Z"
    },
    {
      "no": "10",
      "title": " Vivamus nec mauris vitae sapien cursus elementum. Sed sed suscipit justo, ut tium faucibus dolor at scelerisque",
      "create_time": "2021-05-27T17:13:40Z",
      "update_time": "2021-05-27T17:13:40Z"
    },
    {
      "no": "11",
      "title": " Vivamus nec mauris vitae sapien cursus elementum. Sed sed suscipit justo, ut tium faucibus dolor at scelerisque",
      "create_time": "2021-05-27T17:13:40Z",
      "update_time": "2021-05-27T17:13:40Z"
    },
    {
      "no": "12",
      "title": " Vivamus nec mauris vitae sapien cursus elementum. Sed sed suscipit justo, ut tium faucibus dolor at scelerisque",
      "create_time": "2021-05-27T17:13:40Z",
      "update_time": "2021-05-27T17:13:40Z"
    }
  ],
  "notice": {
    "total": 11,
    "noticelist": [
      {
        "no": 1,
        "title": "[안내]BOBBY 2nd ALBUM [LUCKY MAN]& KIT ALBUM 발매",
        "create_time": "2021-05-27T17:13:40Z",
        "update_time": "2021-05-27T17:13:40Z"
      },
      {
        "no": 2,
        "title": "[안내]B.I 구독 서비스 알림",
        "create_time": "2021-05-27T17:13:40Z",
        "update_time": "2021-05-27T17:13:40Z"
      },
      {
        "no": 3,
        "title": "[안내] BOBY....",
        "create_time": "2021-05-27T17:13:40Z",
        "update_time": "2021-05-27T17:13:40Z"
      },
      {
        "no": 4,
        "title": "[공지] 온라인 콘서트 티켓 오픈 공지",
        "create_time": "2021-05-27T17:13:40Z",
        "update_time": "2021-05-27T17:13:40Z"
      },
      {
        "no": 5,
        "title": "Lorem ipsum dolor sit amet, consectetur adipiscing elit. Aenean ac hendrerit ligula. Proin dignissim mollis odio, eu gravida metus ven",
        "create_time": "2021-05-27T17:13:40Z",
        "update_time": "2021-05-27T17:13:40Z"
      },
      {
        "no": 6,
        "title": "r lorem sodales a. Class aptent taciti sociosqu ad litora tore",
        "create_time": "2021-05-27T17:13:40Z",
        "update_time": "2021-05-27T17:13:40Z"
      },
      {
        "no": 7,
        "title": " non semper lacinia. Proin sit amet hendrerit nulla, nec sollicitudin enim.",
        "create_time": "2021-05-27T17:13:40Z",
        "update_time": "2021-05-27T17:13:40Z"
      },
      {
        "no": 8,
        "title": " Vivamus nec mauris vitae sapien cursus elementum. Sed sed suscipit justo, ut tium faucibus dolor at scelerisque",
        "create_time": "2021-05-27T17:13:40Z",
        "update_time": "2021-05-27T17:13:40Z"
      },
      {
        "no": 9,
        "title": " Vivamus nec mauris vitae sapien cursus elementum. Sed sed suscipit justo, ut tium faucibus dolor at scelerisque",
        "create_time": "2021-05-27T17:13:40Z",
        "update_time": "2021-05-27T17:13:40Z"
      },
      {
        "no": 10,
        "title": " Vivamus nec mauris vitae sapien cursus elementum. Sed sed suscipit justo, ut tium faucibus dolor at scelerisque",
        "create_time": "2021-05-27T17:13:40Z",
        "update_time": "2021-05-27T17:13:40Z"
      },
      {
        "no": 11,
        "title": " Vivamus nec mauris vitae sapien cursus elementum. Sed sed suscipit justo, ut tium faucibus dolor at scelerisque",
        "create_time": "2021-05-27T17:13:40Z",
        "update_time": "2021-05-27T17:13:40Z"
      }
    ]
  },
  "noticedetail": [
    {
      "id": "1",
      "no": "11",
      "title": "[안내]BOBBY 2nd ALBUM [LUCKY MAN]& KIT ALBUM 발매다.",
      "contents": "<h1>이전에 작성한 내용입니다 !!!&nbsp;</h1>\n<p>가나다라마바사</p>"
    },
    {
      "id": "2",
      "no": "2",
      "title": "[안내]B.I 구독 서비스 알림",
      "contents": "<h1>목업 내용 : 이전에 작성한 내용입니다</h1><p>가나다라마바사</p>"
    },
    {
      "id": "3",
      "no": "3",
      "title": "[안내] BOBY....",
      "contents": "<h1>이전에 작성한 내용입니다</h1><p>가나다라마바사</p>"
    },
    {
      "id": "4",
      "no": "4",
      "title": "[안내]BOBBY 2nd ALBUM [LUCKY MAN]& KIT ALBUM 발매",
      "contents": "<h1>이전에 작성한 내용입니다</h1><p>가나다라마바사</p>"
    },
    {
      "id": "5",
      "no": "5",
      "title": "[안내]BOBBY 2nd ALBUM [LUCKY MAN]& KIT ALBUM 발매",
      "contents": "<h1>이전에 작성한 내용입니다</h1><p>가나다라마바사</p>"
    },
    {
      "id": "6",
      "no": "6",
      "title": "[안내]BOBBY 2nd ALBUM [LUCKY MAN]& KIT ALBUM 발매",
      "contents": "<h1>이전에 작성한 내용입니다</h1><p>가나다라마바사</p>"
    },
    {
      "id": "7",
      "no": "7",
      "title": "[안내]BOBBY 2nd ALBUM [LUCKY MAN]& KIT ALBUM 발매",
      "contents": "<h1>이전에 작성한 내용입니다</h1><p>가나다라마바사</p>"
    },
    {
      "id": "3",
      "no": "3",
      "title": "[안내]BOBBY 2nd ALBUM [LUCKY MAN]& KIT ALBUM 발매",
      "contents": "<h1>이전에 작성한 내용입니다</h1><p>가나다라마바사</p>"
    },
    {
      "id": "8",
      "no": "8",
      "title": "[안내]BOBBY 2nd ALBUM [LUCKY MAN]& KIT ALBUM 발매",
      "contents": "<h1>이전에 작성한 내용입니다</h1><p>가나다라마바사</p>"
    },
    {
      "id": "9",
      "no": "9",
      "title": "[안내]BOBBY 2nd ALBUM [LUCKY MAN]& KIT ALBUM 발매",
      "contents": "<h1>이전에 작성한 내용입니다</h1><p>가나다라마바사</p>"
    },
    {
      "id": "10",
      "no": "11",
      "title": "this.$route.params.item",
      "contents": "<h1>이전에 작성한 내용입니다</h1><p>가나다라마바사</p>"
    },
    {
      "id": "10",
      "no": "10",
      "title": "[안내]BOBBY 2nd ALBUM [LUCKY MAN]& KIT ALBUM 발매",
      "contents": "<h1>이전에 작성한 내용입니다</h1><p>가나다라마바사</p>"
    }
  ],
  "artist": {
    "total": "12",
    "artisList": [
      {
        "artistNo": "1",
        "thumbNail": "",
        "artistName": "B.I(비아이)",
        "create_time": "2021-04-15T12:00:00Z",
        "status": true
      },
      {
        "artistNo": "2",
        "thumbNail": "",
        "artistName": "홍길동",
        "create_time": "2021-04-13T12:00:00Z",
        "status": false
      },
      {
        "artistNo": "3",
        "thumbNail": "",
        "artistName": "성춘향",
        "create_time": "2021-04-11T12:00:00Z",
        "status": true
      },
      {
        "artistNo": "4",
        "thumbNail": "",
        "artistName": "이몽룡",
        "create_time": "2021-04-10T12:00:00Z",
        "status": false
      },
      {
        "artistNo": "5",
        "thumbNail": "",
        "artistName": "김영희",
        "create_time": "2021-04-02T12:00:00Z",
        "status": true
      },
      {
        "artistNo": "6",
        "thumbNail": "",
        "artistName": "B.I(비아이)",
        "create_time": "2021-04-15T12:00:00Z",
        "status": true
      },
      {
        "artistNo": "7",
        "thumbNail": "",
        "artistName": "B.I(비아이)",
        "create_time": "2021-04-15T12:00:00Z",
        "status": true
      },
      {
        "artistNo": "8",
        "thumbNail": "",
        "artistName": "B.I(비아이)",
        "create_time": "2021-04-15T12:00:00Z",
        "status": true
      },
      {
        "artistNo": "9",
        "thumbNail": "",
        "artistName": "B.I(비아이)",
        "create_time": "2021-04-15T12:00:00Z",
        "status": true
      },
      {
        "artistNo": "10",
        "thumbNail": "",
        "artistName": "B.I(비아이)",
        "create_time": "2021-04-15T12:00:00Z",
        "status": true
      },
      {
        "artistNo": "11",
        "thumbNail": "",
        "artistName": "B.I(비아이)",
        "create_time": "2021-04-15T12:00:00Z",
        "status": true
      },
      {
        "artistNo": "12",
        "thumbNail": "",
        "artistName": "B.I(비아이)",
        "create_time": "2021-04-15T12:00:00Z",
        "status": true
      }
    ]
  },
  "artistdetail": [
    {
      "id": "1",
      "artistNo": "10",
      "artistName": "B.I(비아이)",
      "thumbNail": "https://www.iokmusic.com/img/index.jpg",
      "intro": "<h1>아티스트 소개글</h1><p>데뷔하다.</p>",
      "snsList": [
        {
          "name": "Youtube",
          "url": "www.youtube.com",
          "show": true
        },
        {
          "name": "Instagram",
          "url": "",
          "show": false
        },
        {
          "name": "Facebook",
          "url": "www.facebook.com",
          "show": true
        },
        {
          "name": "Twitter",
          "url": "",
          "show": false
        },
        {
          "name": "SoundCloud",
          "url": "",
          "show": false
        }
      ],
      "mvList": [
        {
          "no": "1",
          "url": "https://www.youtube.com/haha"
        },
        {
          "no": "2",
          "url": "https://www.youtube.com/haha2"
        },
        {
          "no": "3",
          "url": "https://www.youtube.com/haha3"
        },
        {
          "no": "4",
          "url": "https://www.youtube.com/haha4"
        }
      ],
      "albumList": [
        {
          "no": "1",
          "url": "https://www.youtube.com/haha1",
          "img": "https://camo.githubusercontent.com/100995ad676f7299b746dbe16055485aee91114e14673c7b8dde9bb0c81dc3c4/68747470733a2f2f696d616765732e73667463646e2e6e65742f696d616765732f745f6170702d636f7665722d6c2c665f6175746f2f702f63653265636536302d396233322d313165362d393561622d3030313633656438333365372f3236303636333731302f7468652d746573742d66756e2d666f722d667269656e64732d73637265656e73686f742e6a7067"
        },
        {
          "no": "2",
          "url": "https://www.youtube.com/haha2",
          "img": "https://camo.githubusercontent.com/100995ad676f7299b746dbe16055485aee91114e14673c7b8dde9bb0c81dc3c4/68747470733a2f2f696d616765732e73667463646e2e6e65742f696d616765732f745f6170702d636f7665722d6c2c665f6175746f2f702f63653265636536302d396233322d313165362d393561622d3030313633656438333365372f3236303636333731302f7468652d746573742d66756e2d666f722d667269656e64732d73637265656e73686f742e6a7067"
        }
      ],
      "recordList": [
        {
          "no": "1",
          "contents": "2021.10.02[MINI ALBUM]"
        },
        {
          "no": "2",
          "contents": "2021.10.02[FIRST ALBUM]"
        }
      ],
      "award": "<h1>음악방송</h1><p>데뷔하다.</p>"
    }
  ],
  "artistupload": {
    "id": "upload",
    "artistNo": "11",
    "artistName": "B.I(비아이)",
    "intro": "<h1>아티스트 소개글</h1><p>데뷔하다.</p>",
    "snsList": [
      {
        "name": "Youtube",
        "url": "www.youtube.comdddd",
        "show": true
      },
      {
        "name": "Instagram",
        "url": "",
        "show": false
      },
      {
        "name": "Facebook",
        "url": "www.facebook.com",
        "show": true
      },
      {
        "name": "Twitter",
        "url": "",
        "show": false
      },
      {
        "name": "SoundCloud",
        "url": "",
        "show": false
      }
    ],
    "mvList": [
      {
        "no": "1",
        "url": "https://www.youtube.com/haha"
      },
      {
        "no": "2",
        "url": "https://www.youtube.com/haha2"
      },
      {
        "no": "3",
        "url": "https://www.youtube.com/haha3"
      },
      {
        "no": "4",
        "url": "https://www.youtube.com/haha4"
      }
    ],
    "albumList": [
      {
        "no": "1",
        "url": "https://www.youtube.com/haha1",
        "img": "https://camo.githubusercontent.com/100995ad676f7299b746dbe16055485aee91114e14673c7b8dde9bb0c81dc3c4/68747470733a2f2f696d616765732e73667463646e2e6e65742f696d616765732f745f6170702d636f7665722d6c2c665f6175746f2f702f63653265636536302d396233322d313165362d393561622d3030313633656438333365372f3236303636333731302f7468652d746573742d66756e2d666f722d667269656e64732d73637265656e73686f742e6a7067"
      },
      {
        "no": "2",
        "url": "https://www.youtube.com/haha2",
        "img": "https://camo.githubusercontent.com/100995ad676f7299b746dbe16055485aee91114e14673c7b8dde9bb0c81dc3c4/68747470733a2f2f696d616765732e73667463646e2e6e65742f696d616765732f745f6170702d636f7665722d6c2c665f6175746f2f702f63653265636536302d396233322d313165362d393561622d3030313633656438333365372f3236303636333731302f7468652d746573742d66756e2d666f722d667269656e64732d73637265656e73686f742e6a7067"
      }
    ],
    "recordList": [
      {
        "no": "1",
        "contents": "2021.10.02[MINI ALBUM]"
      },
      {
        "no": "2",
        "contents": "2021.10.02[FIRST ALBUM]"
      }
    ],
    "award": "<h1>음악방송</h1><p>데뷔하다.</p>"
  },
  "about": {
    "aboutNo": "1",
    "contents": "<p>새로운 내용을 작성해요.</p>"
  },
  "contact": {
    "contactNo": "1",
    "logo": "https://camo.githubusercontent.com/100995ad676f7299b746dbe16055485aee91114e14673c7b8dde9bb0c81dc3c4/68747470733a2f2f696d616765732e73667463646e2e6e65742f696d616765732f745f6170702d636f7665722d6c2c665f6175746f2f702f63653265636536302d396233322d313165362d393561622d3030313633656438333365372f3236303636333731302f7468652d746573742d66756e2d666f722d667269656e64732d73637265656e73686f742e6a7067",
    "email": "iok@music.com",
    "snsList": [
      {
        "name": "Youtube",
        "url": "www.youtube.com/iokmusic",
        "show": true
      },
      {
        "name": "Instagram",
        "url": "www.instagram.com/iokmusic",
        "show": true
      },
      {
        "name": "Facebook",
        "url": "",
        "show": false
      },
      {
        "name": "Twitter",
        "url": "",
        "show": false
      },
      {
        "name": "SoundCloud",
        "url": "",
        "show": false
      }
    ]
  },
  "subscribe": [
    {
      "id": "open",
      "data": {
        "isOpen": true,
        "startAt": "2021-04-21T15:00:00.000Z",
        "endAt": "2021-04-29T15:00:00.000Z"
      }
    },
    {
      "id": "list",
      "data": {
        "total": 499,
        "users": [
          "test001@naver.com",
          "test002@naver.com",
          "test003@naver.com",
          "test004@naver.com",
          "test005@naver.com",
          "test006@naver.com",
          "test007@naver.com",
          "test008@naver.com",
          "test009@naver.com",
          "test010@naver.com",
          "test011@naver.com",
          "test012@naver.com",
          "test013@naver.com",
          "test014@naver.com",
          "test015@naver.com",
          "test016@naver.com",
          "test017@naver.com",
          "test018@naver.com",
          "test019@naver.com",
          "test020@naver.com",
          "test021@naver.com"
        ]
      }
    }
  ],
  "admin": {
    "count": "20",
    "userlist": [
      {
        "email": "admin1@iokmusic.com",
        "division": "음원사업부",
        "name": "홍길동",
        "auth": "최고관리자",
        "lastAction": "2021-04-15T12:00:00Z"
      },
      {
        "email": "admi2n@iokmusic.com",
        "division": "음원사업부",
        "name": "홍길동",
        "auth": "관리자",
        "lastAction": "2021-04-15T12:00:00Z"
      },
      {
        "email": "admin3333@iokmusic.com",
        "division": "음원사업부",
        "name": "홍길동",
        "auth": "서브관리자",
        "lastAction": "2021-04-15T12:00:00Z"
      },
      {
        "email": "admi4444n@iokmusic.com",
        "division": "음원사업부",
        "name": "홍길동",
        "auth": "승인 요청 중",
        "lastAction": "2021-04-15T12:00:00Z"
      }
    ]
  },
  "approval": {
    "count": "20",
    "contentList": [
      {
        "id": "1",
        "contents": "ARTIST / B.I(비아이) / 썸네일, 소개글, M/V 변경 요청",
        "email": "abcd@example.com",
        "division": "음원사업부",
        "name": "홍길동",
        "date": "2021-04-15T12:00:00Z",
        "status": "ready"
      },
      {
        "id": "1",
        "contents": "ABOUT IOK / 내용 변경 요청",
        "email": "abcd@example.com",
        "division": "음원사업부",
        "name": "홍길동",
        "date": "2021-04-15T12:00:00Z",
        "status": "ready"
      },
      {
        "id": "1",
        "contents": "CONTACT US / SNS 링크 변경 요청",
        "email": "abcd@example.com",
        "division": "음원사업부",
        "name": "홍길동",
        "date": "2021-04-15T12:00:00Z",
        "status": "ready"
      },
      {
        "id": "1",
        "contents": "admin@iokmusic.com",
        "email": "abcd@example.com",
        "division": "음원사업부",
        "name": "홍길동",
        "date": "2021-04-15T12:00:00Z",
        "status": "ready"
      }
    ]
  },
  "upload": {}
}